LICENSE
README.md
setup.py
pygame_simple_core/__init__.py
pygame_simple_core/core.py
pygame_simple_core.egg-info/PKG-INFO
pygame_simple_core.egg-info/SOURCES.txt
pygame_simple_core.egg-info/dependency_links.txt
pygame_simple_core.egg-info/requires.txt
pygame_simple_core.egg-info/top_level.txt
pygame_simple_core/tools/__init__.py
pygame_simple_core/tools/font_finder.py
pygame_simple_core/tools/font_loader.py
pygame_simple_core/tools/scheduled_event.py
pygame_simple_core/widgets/__init__.py
pygame_simple_core/widgets/button.py
pygame_simple_core/widgets/container.py
pygame_simple_core/widgets/fps_counter.py
pygame_simple_core/widgets/image.py
pygame_simple_core/widgets/text.py