Metadata-Version: 2.1
Name: pygame-simple-core
Version: 0.2.1
Summary: a easy to use framework to fastly make games with pygame
Home-page: UNKNOWN
Author: Vinicius Putti Morais
Author-email: viniputtim@gmail.com
License: MIT license
Keywords: pygame
Platform: UNKNOWN
License-File: LICENSE
